sitelle/__init__.py
sitelle/constants.py
sitelle/fit.py
sitelle/nburst.py
sitelle/parallel.py
sitelle/plot.py
sitelle/region.py
sitelle/source.py
sitelle/utils.py
sitelle/version.py
sitelle-0.2.dist-info/DESCRIPTION.rst
sitelle-0.2.dist-info/METADATA
sitelle-0.2.dist-info/RECORD
sitelle-0.2.dist-info/WHEEL
sitelle-0.2.dist-info/metadata.json
sitelle-0.2.dist-info/top_level.txt
