Metadata-Version: 2.0
Name: sitelle
Version: 0.2
Summary: Helper functions to work with M31 observations on SITELLE
Home-page: https://gitlab.ethz.ch/blaunet/sitelle
Author: Barthelemy Launet
Author-email: barthelemy.launet@obspm.fr
License: UNKNOWN
Platform: any
